hackernews500kindex/cli.py
hackernews500kindex/index.py
hackernews500kindex-0.1.0.dist-info/METADATA
hackernews500kindex-0.1.0.dist-info/WHEEL
hackernews500kindex-0.1.0.dist-info/entry_points.txt
hackernews500kindex-0.1.0.dist-info/top_level.txt
hackernews500kindex-0.1.0.dist-info/RECORD
